{
    "avg": {
        "wmc": 8.2,
        "ccn": 5.55,
        "bugs": 0.16,
        "kanDefect": 0.44,
        "relativeSystemComplexity": 113.49,
        "relativeDataComplexity": 1.84,
        "relativeStructuralComplexity": 111.65,
        "volume": 468.46,
        "commentWeight": 31.22,
        "intelligentContent": 66.7,
        "lcom": 1.2,
        "instability": 0.57,
        "afferentCoupling": 1.3,
        "efferentCoupling": 2.55,
        "difficulty": 8.19,
        "mi": 97.12,
        "distance": 0.33,
        "incomingCDep": 1.8,
        "incomingPDep": 0.8,
        "outgoingCDep": 4,
        "outgoingPDep": 2.6,
        "classesPerPackage": 4.2
    },
    "sum": {
        "loc": 1363,
        "cloc": 398,
        "lloc": 967,
        "nbMethods": 73,
        "nbClasses": 20,
        "nbInterfaces": 1,
        "nbPackages": 5,
        "violations": {
            "total": 7,
            "information": 0,
            "warning": 6,
            "error": 1,
            "critical": 0
        }
    }
}